Metadata-Version: 2.4
Name: roundtable-ai
Version: 0.7.0
Summary: Zero-configuration MCP server that unifies multiple AI coding assistants (Codex, Claude Code, Cursor, Gemini) through intelligent auto-discovery and standardized interface
Author-email: Roundtable AI <support@askbudi.ai>
Project-URL: Homepage, https://askbudi.ai/roundtable
Project-URL: Repository, https://github.com/askbudi/roundtable
Project-URL: Documentation, https://askbudi.ai/roundtable
Classifier: Development Status :: 3 - Alpha
Classifier: Intended Audience :: Developers
Classifier: License :: OSI Approved :: GNU Affero General Public License v3
Classifier: Programming Language :: Python :: 3
Classifier: Programming Language :: Python :: 3.10
Classifier: Programming Language :: Python :: 3.11
Classifier: Programming Language :: Python :: 3.12
Classifier: Topic :: Software Development :: Code Generators
Classifier: Topic :: Software Development :: Libraries :: Application Frameworks
Classifier: Topic :: System :: Systems Administration
Classifier: Environment :: Console
Classifier: Framework :: AsyncIO
Requires-Python: >=3.10
Requires-Dist: fastmcp>=0.1.0
Requires-Dist: aiohttp>=3.8.0
Requires-Dist: claude_code_sdk
Requires-Dist: pydantic>=2.7
Requires-Dist: tinyagent-py>=0.1.18
Requires-Dist: httpx>=0.27.0
Provides-Extra: dev
Requires-Dist: pytest>=7.0.0; extra == "dev"
Requires-Dist: pytest-asyncio>=0.21.0; extra == "dev"
Requires-Dist: pytest-mock>=3.10.0; extra == "dev"
Requires-Dist: black>=23.0.0; extra == "dev"
Requires-Dist: ruff>=0.1.0; extra == "dev"
Requires-Dist: mypy>=1.0.0; extra == "dev"
Requires-Dist: pre-commit>=3.0.0; extra == "dev"
